Metadata-Version: 2.1
Name: dashtable2
Version: 1.4.17
Summary: A library for converting HTML/Markdown/RST tables into ASCII tables and vice versa, rowspan and colspan allowed!
Home-page: https://github.com/PasaOpasen/dashtable2
Author: doakey3 & gustavklopp & pasaopasen
Author-email: qtckpuhdsa@gmail.com
License: MIT
Keywords: text table,conversion,documentation
Classifier: Programming Language :: Python :: 3.8
Classifier: License :: OSI Approved :: MIT License
Classifier: Operating System :: OS Independent
Classifier: Topic :: Software Development :: Libraries :: Python Modules
License-File: LICENSE.txt
Requires-Dist: bs4
Requires-Dist: docutils
Requires-Dist: numpy
Requires-Dist: typing-extensions
